essm_jax/__init__.py
essm_jax/dual_essm.py
essm_jax/essm.py
essm_jax/jvp_op.py
essm_jax/pytee_utils.py
essm_jax/tests/__init__.py
essm_jax/tests/test_essm.py
essm_jax/tests/test_jvp_op.py
essm_jax/tests/test_pytree_utils.py
essm_jax-1.0.2.dist-info/LICENSE
essm_jax-1.0.2.dist-info/METADATA
essm_jax-1.0.2.dist-info/WHEEL
essm_jax-1.0.2.dist-info/top_level.txt
essm_jax-1.0.2.dist-info/RECORD
