Metadata-Version: 2.1
Name: essm_jax
Version: 1.0.2
Summary: Extended State Space Modelling in JAX
Author-email: "Joshua G. Albert" <albert@strw.leidenuniv.nl>
License: Apache Software License
Project-URL: Homepage, https://github.com/joshuaalbert/essm_jax
Keywords: kalman,non-linear,EKF,modelling
Classifier: Programming Language :: Python :: 3
Classifier: License :: OSI Approved :: Apache Software License
Classifier: Operating System :: OS Independent
Requires-Python: >3.9
License-File: LICENSE
Provides-Extra: examples
